curricula_grade/__init__.py
curricula_grade/exception.py
curricula_grade/models.py
curricula_grade/resource.py
curricula_grade/run.py
curricula_grade/shell.py
curricula_grade/shortcuts.py
curricula_grade/version.py
curricula_grade/cleanup/__init__.py
curricula_grade/common/__init__.py
curricula_grade/common/process.py
curricula_grade/grader/__init__.py
curricula_grade/grader/report.py
curricula_grade/grader/task/__init__.py
curricula_grade/grader/task/collection.py
curricula_grade/grader/task/dependency.py
curricula_grade/grader/task/filter.py
curricula_grade/grader/task/registrar.py
curricula_grade/setup/__init__.py
curricula_grade/setup/common.py
curricula_grade/test/__init__.py
curricula_grade/test/code/__init__.py
curricula_grade/test/complexity/__init__.py
curricula_grade/test/complexity/common.py
curricula_grade/test/correctness/__init__.py
curricula_grade/test/correctness/common.py
curricula_grade/test/memory/__init__.py
curricula_grade/test/memory/common.py
curricula_grade/tools/__init__.py
curricula_grade/tools/compare.py
curricula_grade/tools/diagnose.py
curricula_grade/tools/summarize.py
curricula_grade-2.1.1.dist-info/LICENSE
curricula_grade-2.1.1.dist-info/METADATA
curricula_grade-2.1.1.dist-info/WHEEL
curricula_grade-2.1.1.dist-info/top_level.txt
curricula_grade-2.1.1.dist-info/RECORD
