Metadata-Version: 2.1
Name: curricula-grade
Version: 2.1.1
Summary: A grading toolkit for evaluating student code.
Home-page: https://github.com/curriculagg/curricula
Author: Noah Kim
Author-email: noahbkim@gmail.com
License: UNKNOWN
Platform: UNKNOWN
Requires-Python: >=3.9
Requires-Dist: curricula (~=2.1.1)
